carthooks/__init__.py
carthooks/sdk.py
carthooks/watcher/__init__.py
carthooks/watcher/logger.py
carthooks/watcher/sqs_listener.py
carthooks/watcher/sqs_message.py
carthooks/watcher/watch_renewal.py
carthooks/watcher/watcher.py
carthooks-0.2.4.dist-info/METADATA
carthooks-0.2.4.dist-info/WHEEL
carthooks-0.2.4.dist-info/top_level.txt
carthooks-0.2.4.dist-info/RECORD
