Metadata-Version: 2.4
Name: carthooks
Version: 0.2.4
Summary: Carthooks Python SDK with Watcher for real-time data monitoring
Author: Carthooks
Author-email: developer@carthooks.com
License: MIT
Classifier: Programming Language :: Python :: 3
Classifier: License :: OSI Approved :: MIT License
Requires-Dist: httpx[http2]>=0.24.0
Requires-Dist: boto3>=1.26.0
Dynamic: author
Dynamic: author-email
Dynamic: classifier
Dynamic: description
Dynamic: description-content-type
Dynamic: license
Dynamic: requires-dist
Dynamic: summary
